{
    "mood": "relaxed",
    "instrument_vector": [
        0,
        0,
        0,
        0
    ],
    "instruments": {
        "Lead 1 (square)": [
            71408,
            33014,
            2683,
            71416,
            1352,
            19685,
            2683,
            71464,
            1352,
            24064,
            2683,
            31765,
            2683,
            35809,
            71411,
            24040,
            2683,
            71410,
            1352,
            33014,
            2683,
            71416,
            1352,
            19685,
            2683,
            14885,
            2683,
            31765,
            71411,
            33014,
            2683,
            71416,
            1352,
            19685,
            2683,
            71464,
            1352,
            24064,
            2683,
            31765,
            2683,
            35809,
            71413,
            13997,
            2683,
            23670,
            1352,
            19685,
            2683,
            71464,
            1352,
            17101,
            2683,
            56102,
            2683,
            31770,
            71415,
            24083,
            2683,
            23661,
            2683,
            25521,
            2683,
            30178,
            1352,
            34314,
            2683,
            35809,
            2683,
            20602,
            71411,
            33014,
            2683,
            71416,
            1352,
            19685,
            2683,
            71464,
            1352,
            24064,
            2683,
            31765,
            2683,
            35809,
            71411,
            24040,
            2683,
            71410,
            1352,
            33014,
            2683,
            71416,
            1352,
            19685,
            2683,
            14885,
            2683,
            31765,
            71411,
            33014,
            2683,
            71416,
            1352,
            19685,
            2683,
            71464,
            1352,
            24064,
            2683,
            31765,
            2683,
            35809,
            71417,
            45262,
            2683,
            23616,
            1352,
            42988,
            1352,
            46440,
            2683,
            71465,
            1352,
            42693,
            1352,
            45262,
            2683,
            23616,
            1352,
            42988,
            1352,
            45262,
            2683,
            23616,
            1352,
            42988,
            1352,
            57637,
            2683,
            71420,
            1352,
            42950,
            1352,
            71374,
            2683,
            71418,
            1352,
            42687,
            1352,
            45253,
            2683,
            71419,
            1352,
            26913,
            1352,
            46440,
            2683,
            71465,
            1352,
            42693,
            1352,
            45262,
            2683,
            23616,
            1352,
            42988,
            1352,
            46440,
            2683,
            71465,
            1352,
            42693,
            1352,
            45262,
            2683,
            23616,
            1352,
            42988,
            1352,
            45262,
            2683,
            23616,
            1352,
            42988,
            1352,
            57637,
            2683,
            71420,
            1352,
            42950,
            1352,
            24708,
            2683,
            71466,
            1352,
            31341,
            1352,
            45262,
            2683,
            23616,
            1352,
            42988,
            1352,
            45262,
            2683,
            23616,
            1352,
            42988,
            1352,
            45262,
            2683,
            23616,
            1352,
            42988,
            1352,
            45262,
            2683,
            23616,
            1352,
            42988,
            1352,
            45262,
            2683,
            23616,
            1352,
            42988,
            1352,
            45262,
            2683,
            23616,
            1352,
            42988,
            1352,
            45262,
            2683,
            23616,
            1352,
            42988,
            1352,
            45262,
            2683,
            23616,
            1352,
            42988,
            1352,
            46440,
            2683,
            71465,
            1352,
            42693,
            1352,
            46440,
            2683,
            71465,
            1352,
            42693,
            1352,
            71467,
            2683,
            71468,
            1352,
            42679,
            1352,
            71467,
            2683,
            71468,
            1352,
            42679,
            1352,
            71467,
            2683,
            71468,
            1352,
            42679,
            1352,
            71467,
            2683,
            71468,
            1352,
            42679,
            1352,
            24708,
            2683,
            71466,
            1352,
            31341,
            1352,
            24708,
            2683,
            71466,
            1352,
            31341
        ],
        "Lead 2 (sawtooth)": [
            1007,
            58181,
            5655,
            22959,
            1765,
            8908,
            2439,
            26540,
            1996,
            20492,
            717,
            895,
            1755,
            8908,
            2439,
            26540,
            1996,
            20492,
            528,
            18760,
            717,
            895,
            1755,
            1313,
            2439,
            26540,
            1996,
            18760,
            717,
            895,
            1755,
            1313,
            2439,
            26540,
            1996,
            18760,
            528,
            16515,
            717,
            2602,
            1755,
            8907,
            2439,
            16619,
            1996,
            16515,
            717,
            2602,
            1755,
            8907,
            2439,
            16619,
            1996,
            16515,
            528,
            26540,
            717,
            24854,
            1755,
            895,
            2439,
            18702,
            1996,
            26540,
            717,
            24854,
            1755,
            895,
            2439,
            18702,
            1996,
            26540,
            528,
            27836,
            717,
            25686,
            1755,
            8909,
            2439,
            27961,
            1996,
            27836,
            717,
            25686,
            1755,
            8909,
            2439,
            27961,
            1996,
            27836,
            528,
            26540,
            717,
            895,
            1755,
            895,
            2439,
            26540,
            1996,
            26540,
            717,
            895,
            1755,
            895,
            2439,
            26540,
            1996,
            26540,
            528,
            16515,
            717,
            8907,
            1755,
            8907,
            2439,
            16515,
            1996,
            16515,
            717,
            8907,
            1755,
            8907,
            2439,
            16515,
            1996,
            16515,
            528,
            29396,
            717,
            1313,
            1755,
            8912,
            2439,
            18760,
            1996,
            29396,
            717,
            1313,
            1755,
            8912,
            2439,
            18760,
            1996,
            29396,
            528,
            20492,
            717,
            895,
            1755,
            8908,
            2439,
            26540,
            1996,
            20492,
            717,
            895,
            1755,
            8908,
            2439,
            26540,
            1996,
            20492,
            528,
            18760,
            717,
            895,
            1755,
            1313,
            2439,
            26540,
            1996,
            18760,
            717,
            895,
            1755,
            1313,
            2439,
            26540,
            1996,
            18760,
            528,
            16515,
            717,
            2602,
            1755,
            8907,
            2439,
            16619,
            1996,
            16515,
            717,
            2602,
            1755,
            8907,
            2439,
            16619,
            1996,
            16515,
            528,
            26540,
            717,
            24854,
            1755,
            895,
            2439,
            18702,
            1996,
            26540,
            717,
            24854,
            1755,
            895,
            2439,
            18702,
            1996,
            26540,
            528,
            27836,
            717,
            8909,
            1755,
            8909,
            2439,
            27836,
            1996,
            27836,
            717,
            8909,
            1755,
            8909,
            2439,
            27836,
            1996,
            27836,
            528,
            26540,
            717,
            895,
            1755,
            895,
            2439,
            26540,
            1996,
            26540,
            717,
            895,
            1755,
            895,
            2439,
            26540,
            1996,
            26540,
            528,
            26540,
            717,
            895,
            1755,
            895,
            2439,
            26540,
            1996,
            26540,
            717,
            895,
            1755,
            895,
            2439,
            26540,
            1996,
            26540,
            11207,
            20500,
            717,
            8914,
            1765,
            8908,
            2439,
            16540,
            3606,
            71303,
            6122,
            26540,
            717,
            24854,
            1755,
            895,
            2439,
            18702,
            1996,
            26540,
            717,
            24854,
            1755,
            895,
            2439,
            18702,
            1996,
            26540,
            528,
            16619,
            717,
            2602,
            1755,
            2602,
            2439,
            16619,
            1996,
            16619,
            717,
            2602,
            1755,
            2602,
            2439,
            16619,
            1996,
            16619,
            528,
            18702,
            717,
            24854,
            1755,
            24854,
            2439,
            18702,
            1996,
            18702,
            717,
            24854,
            1755,
            24854,
            2439,
            18702,
            1996,
            18702,
            528,
            29396,
            717,
            8907,
            1755,
            8912,
            2439,
            16515,
            1996,
            29396,
            717,
            8907,
            1755,
            8912,
            2439,
            16515,
            1996,
            29396,
            528,
            26540,
            717,
            24854,
            1755,
            895,
            2439,
            18702,
            1996,
            26540,
            717,
            24854,
            1755,
            895,
            2439,
            18702,
            1996,
            26540,
            528,
            26540,
            717,
            24854,
            1755,
            895,
            2439,
            18702,
            1996,
            26540,
            717,
            24854,
            1755,
            895,
            2439,
            18702,
            1996,
            26540,
            528,
            26540,
            717,
            2602,
            1755,
            895,
            2439,
            16619,
            1996,
            26540,
            717,
            2602,
            1755,
            895,
            2439,
            16619,
            1996,
            26540,
            2102,
            4931,
            2439,
            26549,
            2439,
            895,
            2439,
            19898,
            717,
            2602,
            2439,
            12312,
            2439,
            31274,
            6122,
            20492,
            717,
            895,
            1755,
            8908,
            2439,
            26540,
            1996,
            20492,
            717,
            895,
            1755,
            8908,
            2439,
            26540,
            1996,
            20492,
            528,
            18760,
            717,
            895,
            1755,
            1313,
            2439,
            26540,
            1996,
            18760,
            717,
            895,
            1755,
            1313,
            2439,
            26540,
            1996,
            18760,
            528,
            16515,
            717,
            2602,
            1755,
            8907,
            2439,
            16619,
            1996,
            16515,
            717,
            2602,
            1755,
            8907,
            2439,
            16619,
            1996,
            16515,
            528,
            26540,
            717,
            24854,
            1755,
            895,
            2439,
            18702,
            1996,
            26540,
            717,
            24854,
            1755,
            895,
            2439,
            18702,
            1996,
            26540,
            528,
            27836,
            717,
            25686,
            1755,
            8909,
            2439,
            27961,
            1996,
            27836,
            717,
            25686,
            1755,
            8909,
            2439,
            27961,
            1996,
            27836,
            528,
            26540,
            717,
            895,
            1755,
            895,
            2439,
            26540,
            1996,
            26540,
            717,
            895,
            1755,
            895,
            2439,
            26540,
            1996,
            26540,
            528,
            16515,
            717,
            8907,
            1755,
            8907,
            2439,
            16515,
            1996,
            16515,
            717,
            8907,
            1755,
            8907,
            2439,
            16515,
            1996,
            16515,
            528,
            29396,
            717,
            1313,
            1755,
            8912,
            2439,
            18760,
            1996,
            29396,
            717,
            1313,
            1755,
            8912,
            2439,
            18760,
            1996,
            29396,
            528,
            20492,
            717,
            895,
            1755,
            8908,
            2439,
            26540,
            1996,
            20492,
            717,
            895,
            1755,
            8908,
            2439,
            26540,
            1996,
            20492,
            528,
            18760,
            717,
            895,
            1755,
            1313,
            2439,
            26540,
            1996,
            18760,
            717,
            895,
            1755,
            1313,
            2439,
            26540,
            1996,
            18760,
            528,
            16515,
            717,
            2602,
            1755,
            8907,
            2439,
            16619,
            1996,
            16515,
            717,
            2602,
            1755,
            8907,
            2439,
            16619,
            1996,
            16515,
            528,
            26540,
            717,
            24854,
            1755,
            895,
            2439,
            18702,
            1996,
            26540,
            717,
            24854,
            1755,
            895,
            2439,
            18702,
            1996,
            26540,
            528,
            27836,
            717,
            8909,
            1755,
            8909,
            2439,
            27836,
            1996,
            27836,
            717,
            8909,
            1755,
            8909,
            2439,
            27836,
            1996,
            27836,
            528,
            26540,
            717,
            895,
            1755,
            895,
            2439,
            26540,
            1996,
            26540,
            717,
            895,
            1755,
            895,
            2439,
            26540,
            1996,
            26540,
            528,
            26540,
            717,
            895,
            1755,
            895,
            2439,
            26540,
            1996,
            26540,
            717,
            895,
            1755,
            895,
            2439,
            26540,
            1996,
            26540,
            11207,
            20500,
            717,
            8914,
            1765,
            8910,
            717,
            16540,
            3606,
            71304,
            717,
            71305,
            717,
            71306,
            717,
            71307,
            717,
            71308,
            717,
            71309,
            717,
            71306,
            717,
            71310,
            717,
            19898,
            2439,
            895,
            717,
            19898,
            2439,
            2602,
            717,
            49394,
            2439,
            25686,
            717,
            10924,
            2439,
            25063
        ],
        "Synth Bass 1": [
            37121,
            4549,
            36422,
            2160,
            6386,
            8561,
            6386,
            2160,
            37122,
            2160,
            8131,
            2158,
            18472,
            2160,
            4690,
            8561,
            4690,
            2160,
            10981,
            2160,
            14308,
            2158,
            17514,
            2160,
            10612,
            8561,
            10612,
            2160,
            37123,
            2160,
            14312,
            2158,
            37124,
            2160,
            10608,
            8561,
            10608,
            2160,
            30422,
            2160,
            9293,
            2158,
            18477,
            2160,
            14023,
            8561,
            14023,
            2160,
            5871,
            2160,
            9531,
            2158,
            17511,
            2160,
            9547,
            8561,
            9547,
            2160,
            5870,
            2160,
            9293,
            2158,
            18477,
            2160,
            14023,
            8561,
            14023,
            2160,
            5871,
            2160,
            14312,
            2158,
            37124,
            2160,
            10608,
            8561,
            10608,
            2160,
            30422,
            2160,
            7965,
            2158,
            6304,
            2160,
            6386,
            8561,
            6386,
            2160,
            37122,
            2160,
            8131,
            2158,
            18472,
            2160,
            4690,
            8561,
            4690,
            2160,
            10981,
            2160,
            14308,
            2158,
            17514,
            2160,
            10612,
            8561,
            10612,
            2160,
            37123,
            2160,
            14312,
            2158,
            37124,
            2160,
            10608,
            8561,
            10608,
            2160,
            30422,
            2160,
            9293,
            2158,
            18477,
            2160,
            14023,
            8561,
            14023,
            2160,
            5871,
            2160,
            9531,
            2158,
            17511,
            2160,
            9547,
            8561,
            9547,
            2160,
            5870,
            2160,
            14312,
            2158,
            37124,
            2160,
            10608,
            8561,
            10608,
            2160,
            30422,
            2160,
            8350,
            2158,
            6304,
            2160,
            6404,
            8561,
            6386,
            2160,
            37122,
            2160,
            14312,
            2158,
            37124,
            2160,
            10608,
            8561,
            10608,
            2160,
            30422,
            2160,
            14312,
            2158,
            37124,
            2160,
            10608,
            8561,
            10608,
            2160,
            30422,
            2160,
            9564,
            2158,
            14874,
            2160,
            4698,
            8561,
            4698,
            2160,
            37125,
            2160,
            9564,
            2158,
            14874,
            2160,
            4698,
            8561,
            4698,
            2160,
            37125,
            2160,
            14312,
            2158,
            37124,
            2160,
            10608,
            8561,
            10608,
            2160,
            30422,
            2160,
            14312,
            2158,
            37124,
            2160,
            10608,
            8561,
            10608,
            2160,
            30422,
            2160,
            14312,
            2158,
            37124,
            2160,
            10608,
            8561,
            10608,
            2160,
            30422,
            2160,
            8350,
            2158,
            2330,
            2158,
            6404,
            8561,
            6386,
            2160,
            37122,
            2160,
            7965,
            2158,
            6304,
            2160,
            6386,
            8561,
            6386,
            2160,
            37122,
            2160,
            8131,
            2158,
            18472,
            2160,
            4690,
            8561,
            4690,
            2160,
            10981,
            2160,
            14308,
            2158,
            17514,
            2160,
            10612,
            8561,
            10612,
            2160,
            37123,
            2160,
            14312,
            2158,
            37124,
            2160,
            10608,
            8561,
            10608,
            2160,
            30422,
            2160,
            9293,
            2158,
            18477,
            2160,
            14023,
            8561,
            14023,
            2160,
            5871,
            2160,
            9531,
            2158,
            17511,
            2160,
            9547,
            8561,
            9547,
            2160,
            5870,
            2160,
            9293,
            2158,
            18477,
            2160,
            14023,
            8561,
            14023,
            2160,
            5871,
            2160,
            14312,
            2158,
            37124,
            2160,
            10608,
            8561,
            10608,
            2160,
            30422,
            2160,
            7965,
            2158,
            6304,
            2160,
            6386,
            8561,
            6386,
            2160,
            37122,
            2160,
            8131,
            2158,
            18472,
            2160,
            4690,
            8561,
            4690,
            2160,
            10981,
            2160,
            14308,
            2158,
            17514,
            2160,
            10612,
            8561,
            10612,
            2160,
            37123,
            2160,
            14312,
            2158,
            37124,
            2160,
            10608,
            8561,
            10608,
            2160,
            30422,
            2160,
            9293,
            2158,
            18477,
            2160,
            14023,
            8561,
            14023,
            2160,
            5871,
            2160,
            9531,
            2158,
            17511,
            2160,
            9547,
            8561,
            9547,
            2160,
            5870,
            2160,
            14312,
            2158,
            37124,
            2160,
            10608,
            8561,
            10608,
            2160,
            30422,
            2160,
            8350,
            2158,
            2330,
            2158,
            6404,
            8561,
            6399,
            2158,
            37126,
            2158,
            7965,
            2160,
            6304,
            2158,
            6399,
            5344,
            6399,
            2158,
            37126,
            2158,
            7965,
            2160,
            6304,
            2158,
            6399,
            5344,
            6399,
            2158,
            37126,
            2158,
            7965,
            2160,
            6304,
            2158,
            6399,
            5344,
            6399,
            2158,
            37126,
            2158,
            7965,
            2160,
            6304,
            2158,
            6399,
            28,
            17108,
            2160,
            37127,
            2158,
            7965,
            2160,
            6304,
            2158,
            6399,
            28,
            17108,
            2160,
            37127,
            2158,
            7965,
            2160,
            6304,
            2158,
            6399,
            5344,
            6399,
            2158,
            37126,
            2158,
            7965,
            2160,
            6304,
            2158,
            6399,
            28,
            17108,
            2160,
            37127,
            2158,
            7965,
            2160,
            6304,
            2158,
            6399,
            5344,
            6399,
            2158,
            37126,
            2158,
            9293,
            2160,
            2358,
            2158,
            6399,
            2158,
            6453,
            2158,
            9531,
            2160,
            2374,
            2158,
            6399,
            2158,
            6437,
            2158,
            9564,
            2160,
            2376,
            2158,
            16316,
            2158,
            6425,
            2158,
            15705,
            2160,
            4042,
            2158,
            16316,
            2158,
            6399,
            2158,
            14312,
            2160,
            2716,
            2158,
            6425,
            2158,
            3126,
            2158,
            13004,
            2160,
            2421,
            2158,
            6425,
            2158,
            349,
            2158,
            9293,
            2160,
            2358,
            2158,
            6425,
            2158,
            6453,
            2158,
            9531,
            2160,
            2374,
            2158,
            6399,
            2158,
            6437,
            2158,
            9293,
            2160,
            2358,
            2158,
            6399,
            2158,
            6453,
            2158,
            9531,
            2160,
            2374,
            2158,
            6399,
            2158,
            6437,
            2158,
            9564,
            2160,
            2376,
            2158,
            16316,
            2158,
            6425,
            2158,
            15705,
            2160,
            4042,
            2158,
            16316,
            2158,
            6399,
            2158,
            7956,
            2160,
            793,
            2158,
            16384,
            2158,
            10621,
            2158,
            15705,
            2160,
            4042,
            2158,
            16379,
            2158,
            6399,
            2158,
            9293,
            2160,
            2358,
            2158,
            6399,
            2158,
            6453,
            2158,
            9531,
            2160,
            2374,
            2158,
            6399,
            2158,
            6435,
            2158,
            9564,
            2160,
            2376,
            2158,
            16316,
            2158,
            6425,
            2158,
            9292,
            2160,
            2404,
            2158,
            16316,
            2158,
            4721,
            2158,
            15705,
            2160,
            4042,
            2158,
            16316,
            2158,
            6399,
            2158,
            12999,
            2160,
            3995,
            2158,
            16316,
            2158,
            6373,
            2158,
            7956,
            2160,
            793,
            2158,
            16384,
            2158,
            10621,
            2158,
            8131,
            2160,
            2518,
            2158,
            16379,
            2158,
            10621,
            2158,
            15705,
            2160,
            4042,
            2158,
            16379,
            2158,
            6399,
            2158,
            9292,
            2160,
            2404,
            2158,
            16316,
            2158,
            4721,
            2158,
            9564,
            2160,
            2376,
            2158,
            16316,
            2158,
            6425,
            2158,
            15705,
            2160,
            4042,
            2158,
            16316,
            2158,
            6425,
            2158,
            30605,
            2160,
            4670,
            2158,
            16384,
            2158,
            6425,
            2158,
            7956,
            2160,
            793,
            2158,
            16384,
            2158,
            10621,
            2158,
            15705,
            2160,
            4042,
            2158,
            16379,
            2158,
            6399,
            2158,
            15705,
            2160,
            4042,
            2158,
            16379,
            2158,
            6399
        ],
        "Acoustic Grand Piano": [
            1031,
            2
        ]
    }
}