{
    "mood": "angry",
    "instrument_vector": [
        0,
        0,
        0,
        0
    ],
    "instruments": {
        "Lead 1 (square)": [
            171,
            29757,
            7,
            26067,
            3789,
            33650,
            2174,
            4595,
            84,
            26067,
            9370,
            14736,
            39,
            13791,
            2609,
            13791,
            141,
            18145,
            39,
            33651,
            39,
            21718,
            21625,
            18150,
            39,
            14860,
            2609,
            14860,
            141,
            13791,
            141,
            14837,
            86,
            13789,
            2172,
            18145,
            39,
            14837,
            2609,
            14837,
            141,
            14736,
            39,
            14860,
            84,
            26058,
            5153,
            33652
        ],
        "Lead 2 (sawtooth)": [
            34307,
            34022,
            34308,
            305,
            34015,
            34309,
            305,
            34310,
            329,
            34191,
            1987,
            34311,
            34312,
            329,
            34313,
            34309,
            305,
            34314,
            1316,
            34315,
            34309,
            305,
            34316,
            305,
            34317,
            34318,
            169,
            34319,
            1101,
            34041,
            315,
            34320,
            1808,
            34321,
            2467,
            34041,
            305,
            34322,
            34041,
            305,
            34323,
            305,
            34324
        ],
        "Synth Bass 1": [
            13,
            6702,
            326,
            6701,
            1606,
            12739,
            2183,
            7685,
            15,
            6701,
            3744,
            5448,
            358,
            142,
            2261,
            142,
            20,
            6804,
            358,
            7206,
            358,
            9860,
            14301,
            5429,
            358,
            7675,
            2261,
            7675,
            20,
            142,
            20,
            7674,
            8,
            158,
            1715,
            6804,
            358,
            7674,
            2261,
            7674,
            20,
            5448,
            358,
            7675,
            15,
            9991,
            10313,
            2631
        ],
        "Acoustic Grand Piano": [
            418,
            2
        ]
    }
}