{
    "mood": "happy",
    "instrument_vector": [
        0,
        0,
        0,
        0
    ],
    "instruments": {
        "Lead 1 (square)": [
            44814,
            44815,
            143,
            44816,
            143,
            44817,
            143,
            44815,
            169,
            44818,
            143,
            44819,
            143,
            44820,
            153,
            44821,
            169,
            44822,
            143,
            44823,
            153,
            44824,
            143,
            44825,
            143,
            44826,
            143,
            44827,
            143,
            44828
        ],
        "Lead 2 (sawtooth)": [
            44777,
            12101,
            492,
            44778,
            466,
            44779,
            492,
            12108,
            476,
            12114,
            466,
            12123,
            476,
            104,
            492,
            697,
            466,
            701,
            466,
            12108,
            2439,
            12113,
            476,
            703,
            466,
            81,
            466,
            691,
            492,
            702,
            466,
            12116,
            466,
            12113,
            476,
            12123,
            466,
            81,
            492,
            691,
            466,
            702,
            2439,
            104,
            466,
            10586,
            466,
            703,
            466,
            12108,
            466,
            697,
            476,
            791,
            476,
            81,
            492,
            12107,
            466,
            12118,
            492,
            12119,
            466,
            697,
            717,
            703,
            476,
            104,
            466,
            10586,
            466,
            701,
            476,
            104,
            476,
            12125,
            476,
            703,
            466,
            81,
            466,
            12107,
            466,
            12126,
            466,
            12116,
            476,
            697,
            466,
            703,
            466,
            81,
            466,
            12107,
            492,
            702,
            44780,
            81
        ],
        "Synth Bass 1": [
            7674,
            9336,
            7,
            24226,
            1539,
            9291,
            33,
            9291,
            33,
            11404,
            33,
            2424,
            7,
            5469,
            7,
            2424,
            7,
            9550,
            33,
            10769,
            7,
            2390,
            7,
            791,
            33,
            2419,
            33,
            2359,
            33,
            4056,
            7,
            2422,
            17,
            2419,
            17,
            4697,
            7,
            24227,
            7,
            2404,
            17,
            2419,
            17,
            2424,
            17,
            9296,
            7,
            2419,
            33,
            2694,
            7,
            791,
            33,
            5962,
            2158,
            24228,
            7,
            2358,
            7,
            2424,
            7,
            4056,
            17,
            2382,
            7,
            791,
            7,
            2694,
            7,
            9289,
            7,
            4720,
            7,
            9293,
            33,
            4709,
            7,
            4056,
            17,
            5360,
            7,
            2371,
            7,
            2419,
            33,
            2694,
            7,
            4054,
            7,
            9337,
            33,
            16796,
            7,
            18463,
            17,
            791,
            33,
            791,
            7,
            2359,
            33,
            2424,
            17,
            5469,
            7,
            2424,
            7,
            12849,
            7,
            9297,
            7,
            2396,
            17,
            2419,
            7,
            2419,
            7,
            2358,
            7,
            120,
            7,
            2422,
            17,
            2424,
            7,
            9337,
            33,
            22452,
            7,
            2359,
            33,
            5360,
            17,
            5360,
            17,
            9299,
            17,
            791,
            33,
            2421,
            33,
            791,
            7,
            19584,
            2160,
            24229,
            33,
            4709,
            7,
            4696,
            7,
            4086,
            17,
            2396,
            7,
            3995,
            7,
            2419,
            7,
            3995,
            7,
            2239,
            7,
            12999,
            7,
            4709,
            7,
            27,
            7,
            4739,
            7,
            4696,
            17,
            4674,
            7,
            2404,
            7,
            27,
            33,
            4666,
            7,
            13006,
            17,
            3722,
            17,
            2419,
            33,
            2424,
            7,
            2358,
            7,
            2424,
            7,
            48,
            7,
            5360,
            7,
            9294,
            7,
            10800,
            7,
            2382,
            17,
            791,
            33,
            791,
            7,
            791,
            33,
            15687,
            7,
            5360,
            17,
            5360,
            17,
            9337,
            7,
            24230,
            17,
            791,
            7,
            2419,
            7,
            9296,
            7,
            791,
            7,
            2694,
            33,
            791,
            7,
            9336,
            2158,
            13012,
            7,
            2359,
            7,
            2424,
            7,
            120,
            17,
            2382,
            7,
            791,
            33,
            2694,
            7,
            791,
            33,
            4755,
            7,
            24231,
            7,
            2404,
            7,
            120,
            17,
            2424,
            7,
            2382,
            7,
            791,
            7,
            2694,
            33,
            4041,
            7,
            9534,
            7,
            18099,
            7,
            9299,
            7,
            791,
            7,
            791,
            7,
            11404,
            7,
            2424,
            7,
            5469,
            7,
            2424,
            7,
            156,
            7,
            24232,
            7,
            2404,
            17,
            2965,
            7,
            3995,
            17,
            4709,
            7,
            4086,
            7,
            2424,
            7,
            4696,
            7,
            16382,
            7,
            24233,
            33,
            2404,
            33,
            4706,
            17,
            4706,
            17,
            84,
            7,
            4660,
            7,
            4709,
            7,
            4660,
            33,
            52,
            2158,
            9295,
            7,
            8628,
            7,
            2424,
            7,
            4056,
            7,
            2382,
            17,
            791,
            33,
            2694,
            7,
            791,
            33,
            3189,
            7,
            24228,
            7,
            2358,
            7,
            120,
            17,
            2424,
            7,
            2424,
            7,
            791,
            7,
            791,
            33,
            4041,
            7,
            2358,
            7,
            2358,
            7,
            2358,
            7,
            2421,
            7,
            2421,
            7,
            48,
            7,
            792,
            7,
            792,
            7,
            792,
            7,
            2424,
            7,
            3109,
            17,
            2424,
            7,
            9294,
            7,
            24234,
            7,
            5381,
            7,
            2404,
            7,
            2404,
            7,
            2404,
            7,
            9299,
            7,
            2396,
            7,
            2382,
            7,
            9544,
            33,
            9297,
            17,
            2396,
            17,
            2421,
            33,
            2422,
            7,
            40,
            7,
            4709,
            7,
            2694,
            33,
            4709,
            7,
            9513,
            2158,
            9292,
            33,
            2359,
            7,
            4088,
            7,
            9114,
            7,
            5366,
            7,
            3995,
            33,
            791,
            7,
            2965,
            33,
            10596,
            7,
            9293,
            7,
            4709,
            33,
            10592,
            7,
            4706,
            7,
            4696,
            7,
            4706,
            33,
            2396,
            33,
            4706,
            2160,
            3203,
            33,
            16290,
            7,
            3626,
            7,
            2404,
            7,
            2404,
            7,
            2419,
            7,
            2396,
            7,
            9299,
            7,
            2396,
            7,
            9544,
            7,
            24232,
            7,
            2396,
            17,
            2421,
            33,
            2422,
            7,
            792,
            7,
            48,
            7,
            2696,
            7,
            5381,
            7,
            2537,
            7,
            24235,
            7,
            5381,
            7,
            2695,
            33,
            2695,
            7,
            7586,
            33,
            2716,
            7,
            2716,
            7,
            2716,
            7,
            16380,
            2158,
            5886,
            33,
            791,
            7,
            2695,
            7,
            792,
            7,
            10584,
            7,
            2357,
            7,
            2424,
            7,
            792,
            7,
            2419,
            7,
            3191,
            33,
            24236,
            7,
            2421,
            7,
            4516,
            7,
            2396,
            17,
            2396,
            7,
            2359,
            33,
            4709,
            7,
            2359,
            2160,
            6295,
            33,
            17955,
            7,
            4538,
            7,
            2421,
            7,
            2421,
            7,
            2421,
            7,
            2404,
            7,
            48,
            7,
            2404,
            7,
            5935,
            7,
            10769,
            7,
            2382,
            7,
            2965,
            7,
            2965,
            33,
            4709,
            7,
            84,
            7,
            2424,
            17,
            4696,
            7,
            5935,
            7,
            24232,
            7,
            2404,
            7,
            4674,
            7,
            4674,
            7,
            84,
            7,
            4674,
            7,
            2404,
            7,
            4674,
            7,
            13471,
            7,
            13090,
            7,
            4042,
            7,
            2396,
            7,
            4538,
            7,
            2424,
            7,
            4709,
            7,
            2359,
            33,
            4709,
            7,
            10596,
            17,
            9293,
            33,
            4709,
            7,
            4056,
            17,
            5360,
            17,
            2390,
            17,
            791,
            33,
            2694,
            7,
            791,
            2160,
            6268,
            33,
            9295,
            7,
            3712,
            7,
            2419,
            7,
            2419,
            7,
            2419,
            7,
            2424,
            7,
            5360,
            2160,
            2424,
            17,
            9534,
            7,
            24237,
            7,
            2419
        ],
        "Acoustic Grand Piano": [
            570,
            2
        ]
    }
}