{
    "mood": "happy",
    "instrument_vector": [
        0,
        0,
        0,
        0
    ],
    "instruments": {
        "Lead 1 (square)": [
            14263,
            2609,
            62486,
            2609,
            62487,
            2609,
            1140,
            1166,
            801,
            2609,
            15656,
            2609,
            29298,
            2609,
            62394,
            2609,
            3224,
            2609,
            27028,
            1166,
            62488,
            2609,
            26740,
            2609,
            34839,
            2609,
            62487,
            2609,
            62491,
            1166,
            62492,
            2609,
            20517,
            1166,
            62499,
            1166,
            62494,
            1166,
            28843,
            2609,
            37366,
            1166,
            62495,
            1166,
            37238,
            1166,
            36593,
            1166,
            62496,
            2609,
            37334,
            1166,
            36593,
            2609,
            47765,
            2609,
            62497,
            1166,
            62500,
            1166,
            29298,
            2609,
            62251,
            7,
            753,
            1166,
            15656,
            1166,
            41695,
            2609,
            62501,
            1166,
            45908,
            2609,
            15437,
            1166,
            62494,
            1166,
            62502,
            1166,
            34808,
            1166,
            62490,
            2609,
            6763,
            2609,
            3226,
            2609,
            37354,
            2609,
            28510,
            310,
            28508,
            243,
            62503,
            2609,
            28830,
            1166,
            3221,
            2609,
            28830,
            2609,
            28830,
            4761,
            28830,
            45,
            30013,
            1921,
            3228,
            6496,
            30013,
            2609,
            3228,
            2609,
            28830,
            2609,
            3221,
            1166,
            28830
        ],
        "Lead 2 (sawtooth)": [
            5207,
            36587,
            1004,
            19968,
            2637,
            48433,
            2637,
            3541,
            1004,
            5471,
            6688,
            5724,
            2637,
            20476,
            1004,
            48352,
            2637,
            5466,
            1004,
            22290,
            2637,
            48352,
            153,
            36594,
            2637,
            3520,
            2637,
            5497,
            2637,
            63958,
            6688,
            63959,
            2637,
            16066,
            1004,
            36594,
            1004,
            3527,
            2637,
            22292,
            9344,
            22265,
            1004,
            16066,
            2637,
            63962,
            1004,
            48348,
            1004,
            3541,
            169,
            36594,
            1004,
            50142,
            1004,
            51304,
            2637,
            21852,
            2637,
            63960,
            177,
            36587,
            1004,
            20476,
            1004,
            51336,
            1004,
            3541,
            2637,
            5471,
            6688,
            5495,
            2637,
            7515,
            2637,
            31635,
            2637,
            3541,
            143,
            22293,
            2637,
            3520,
            2637,
            5471,
            1004,
            3501,
            2637,
            19952,
            1004,
            63961,
            3064,
            22267,
            1004,
            3511,
            2637,
            22293,
            1004,
            1165,
            2637,
            3541,
            6688,
            63962,
            2637,
            3520,
            580,
            36594,
            105,
            63963,
            2637,
            22293,
            1004,
            5471,
            2637,
            22293,
            2637,
            22293,
            5104,
            22293,
            181,
            36594,
            2356,
            5470,
            6688,
            36594,
            2637,
            3528,
            2637,
            3541,
            2637,
            5471,
            1004,
            3541
        ],
        "Synth Bass 1": [
            32787,
            13028,
            2255,
            7802,
            2261,
            13028,
            2261,
            13028,
            4050,
            13028,
            9218,
            15784,
            1822,
            7800,
            5227,
            15784,
            2261,
            7800,
            2261,
            13028,
            2261,
            7802,
            2255,
            13028
        ],
        "Acoustic Grand Piano": [
            907,
            2
        ]
    }
}