{
    "mood": "angry",
    "instruments": {
        "Lead 1 (square)": [
            4,
            667,
            44,
            633,
            989,
            702,
            989,
            6943,
            196,
            6943,
            196,
            636,
            196,
            636,
            206,
            6944,
            11,
            634,
            989,
            6945,
            989,
            636,
            196,
            636,
            206,
            6946,
            206,
            636,
            196,
            6947,
            44,
            1070,
            989,
            1139,
            989,
            1394,
            196,
            1394,
            196,
            3272,
            196,
            3272,
            196,
            1369,
            44,
            1070,
            989,
            1139,
            989,
            6948,
            206,
            6948,
            196,
            1394,
            206,
            3032,
            206,
            1331,
            44,
            702,
            2722,
            702,
            989,
            6943,
            196,
            6943,
            196,
            636,
            196,
            636,
            206,
            6949,
            44,
            702,
            2722,
            702,
            989,
            636,
            196,
            636,
            206,
            6950,
            196,
            6943,
            196,
            1369,
            44,
            1070,
            989,
            1139,
            989,
            3272,
            196,
            6948,
            206,
            3032,
            206,
            3032,
            206,
            6951,
            13,
            1070,
            2722,
            1070,
            989,
            1394,
            196,
            1394,
            196,
            1394,
            206,
            3032,
            206,
            3265,
            196,
            6952,
            196,
            3278,
            196,
            3278,
            206,
            6953,
            206,
            6953,
            206,
            6952,
            196,
            3265,
            206,
            6953,
            206,
            6953,
            206,
            3278,
            196,
            3278,
            196,
            6952,
            196,
            6952,
            196,
            3278,
            196,
            3278,
            196,
            6954,
            196,
            6954,
            206,
            1856,
            206,
            1856,
            206,
            5010,
            196,
            6955,
            196,
            6954,
            206,
            1856,
            206,
            5010,
            196,
            6955,
            206,
            1856,
            206,
            1856,
            206,
            6954,
            196,
            6954,
            196,
            5010,
            196,
            5010,
            196,
            6953,
            206,
            3278,
            196,
            3278,
            196,
            3278,
            206,
            3265,
            196,
            6952,
            196,
            3278,
            196,
            3278,
            206,
            3265,
            196,
            6952,
            196,
            3278,
            196,
            3278,
            206,
            6953,
            196,
            3278,
            206,
            6953,
            206,
            3278,
            196,
            5010,
            196,
            5010,
            196,
            1856,
            206,
            6954,
            196,
            6954,
            196,
            6954,
            196,
            5010,
            196,
            5010,
            196,
            6954,
            196,
            6954,
            206,
            1856,
            206,
            1856,
            206,
            6955,
            196,
            5010,
            206,
            1856,
            196,
            6954,
            6956,
            6957,
            6958,
            4,
            6957,
            4,
            6958,
            6959,
            4,
            6960,
            6961,
            4,
            6962,
            6963,
            6964,
            4,
            6964,
            6965,
            6966,
            6967,
            6968,
            6969,
            6970,
            4,
            6971,
            6971,
            4,
            6972,
            4,
            6973,
            6974,
            686,
            6975
        ],
        "Lead 2 (sawtooth)": [
            7268,
            7269,
            163,
            7270,
            163,
            7269,
            7271
        ],
        "Synth Bass 1": [
            4448,
            5299,
            5300,
            5301,
            5,
            5302,
            3,
            5303,
            5304,
            5305,
            96,
            5302,
            5,
            4503,
            5,
            5306,
            5307,
            5308,
            5,
            5309,
            13,
            5310,
            13,
            5311,
            5308,
            5307,
            5302,
            4503,
            2004,
            3,
            5302,
            4702,
            5309,
            13,
            5312,
            5,
            5313,
            5,
            5314,
            5299,
            5300,
            5315,
            51,
            5302,
            5302,
            5316,
            5305,
            3,
            2004,
            5302,
            5,
            4503,
            13,
            5306,
            5309,
            5308,
            51,
            5306,
            5,
            5317,
            13,
            5311,
            3,
            5308,
            5307,
            5303,
            5318,
            3,
            96,
            5303,
            4374,
            3,
            5306,
            5,
            5312,
            5,
            5313,
            5,
            4389,
            5319,
            3846,
            5320,
            5321,
            5322,
            3,
            5323,
            5324,
            5325,
            5326,
            5327,
            5328,
            5320,
            5329,
            3,
            5330,
            5331,
            5332,
            5332,
            3,
            5332,
            5306,
            5,
            5307,
            5312,
            5333,
            5,
            5306,
            5312,
            3,
            5318,
            5309,
            3,
            5303,
            5318,
            5334,
            3,
            5319,
            3846,
            5320,
            5335,
            3,
            5331,
            5326,
            5336,
            3,
            5337,
            5326,
            5338,
            5328,
            5331,
            3,
            5339,
            3,
            5340,
            3,
            5341,
            5342,
            5343,
            5344,
            5345,
            5346,
            5347,
            2048,
            3,
            2004,
            5346,
            3,
            2004,
            5348,
            2004,
            3,
            5349,
            96,
            5350,
            3,
            96,
            5346,
            3,
            2004,
            5348,
            2004,
            5306,
            5351,
            66,
            3,
            5351,
            5306,
            3,
            5305,
            5352,
            5305,
            5307,
            5305,
            3,
            63,
            5353,
            5306,
            5353,
            63,
            3,
            5305,
            5318,
            3,
            5350,
            107,
            2048,
            5308,
            5348,
            87,
            5348,
            5303,
            2048,
            107,
            5350,
            3,
            5302,
            5348,
            87,
            5348,
            5354,
            3,
            5305,
            5352,
            5305,
            5355,
            5305,
            3,
            63,
            5353,
            5356,
            5351,
            3,
            66,
            5351,
            5355,
            5305,
            3,
            63,
            5305,
            3,
            5357,
            601,
            5358
        ],
        "Acoustic Grand Piano": [
            68,
            2
        ]
    }
}